CHANGES.txt
LICENSE.rst
MANIFEST.in
README.rst
setup.py
bin/jukebox
jukebox/__init__.py
jukebox/jukebox.wsgi
jukebox/manage.py
jukebox/settings.py
jukebox/settings_local.example.py
jukebox/urls.py
jukebox.egg-info/PKG-INFO
jukebox.egg-info/SOURCES.txt
jukebox.egg-info/dependency_links.txt
jukebox.egg-info/requires.txt
jukebox.egg-info/top_level.txt
jukebox/jukebox_core/__init__.py
jukebox/jukebox_core/admin.py
jukebox/jukebox_core/api.py
jukebox/jukebox_core/forms.py
jukebox/jukebox_core/models.py
jukebox/jukebox_core/urls.py
jukebox/jukebox_core/utils.py
jukebox/jukebox_core/views.py
jukebox/jukebox_core/docs/API.rst
jukebox/jukebox_core/management/__init__.py
jukebox/jukebox_core/management/commands/__init__.py
jukebox/jukebox_core/management/commands/jukebox_index.py
jukebox/jukebox_core/management/commands/jukebox_setup.py
jukebox/jukebox_core/migrations/0001_initial.py
jukebox/jukebox_core/migrations/0002_auto__del_field_album_Artist.py
jukebox/jukebox_core/migrations/__init__.py
jukebox/jukebox_core/tests/__init__.py
jukebox/jukebox_core/tests/api.py
jukebox/jukebox_core/tests/api_albums.py
jukebox/jukebox_core/tests/api_artists.py
jukebox/jukebox_core/tests/api_favourites.py
jukebox/jukebox_core/tests/api_genres.py
jukebox/jukebox_core/tests/api_history.py
jukebox/jukebox_core/tests/api_queue.py
jukebox/jukebox_core/tests/api_songs.py
jukebox/jukebox_core/tests/api_years.py
jukebox/jukebox_web/__init__.py
jukebox/jukebox_web/urls.py
jukebox/jukebox_web/views.py
jukebox/jukebox_web/locale/de/LC_MESSAGES/django.mo
jukebox/jukebox_web/locale/de/LC_MESSAGES/django.po
jukebox/jukebox_web/locale/de/LC_MESSAGES/djangojs.mo
jukebox/jukebox_web/locale/de/LC_MESSAGES/djangojs.po
jukebox/jukebox_web/locale/en/LC_MESSAGES/django.mo
jukebox/jukebox_web/locale/en/LC_MESSAGES/django.po
jukebox/jukebox_web/locale/en/LC_MESSAGES/djangojs.mo
jukebox/jukebox_web/locale/en/LC_MESSAGES/djangojs.po
jukebox/jukebox_web/static/css/music.css
jukebox/jukebox_web/static/img/arrow_down.png
jukebox/jukebox_web/static/img/arrow_down_active.png
jukebox/jukebox_web/static/img/facebook.png
jukebox/jukebox_web/static/img/favicon.ico
